fsverity_hash.py
fsverity_hash-0.0.5.dist-info/LICENSE.txt
fsverity_hash-0.0.5.dist-info/METADATA
fsverity_hash-0.0.5.dist-info/WHEEL
fsverity_hash-0.0.5.dist-info/top_level.txt
fsverity_hash-0.0.5.dist-info/RECORD
