Metadata-Version: 2.1
Name: fsverity-hash
Version: 0.0.5
Summary: fs-verity digest implementation for Python
Author-email: Alex Willmer <alex@moreati.org.uk>
Maintainer-email: Alex Willmer <alex@moreati.org.uk>
License: MIT License
Project-URL: Homepage, https://github.com/moreati/fsverity-hash
Project-URL: Source, https://github.com/moreati/fsverity-hash
Project-URL: Tracker, https://github.com/moreati/fsverity-hash/issues
Classifier: Development Status :: 3 - Alpha
Classifier: Intended Audience :: Developers
Classifier: License :: OSI Approved :: MIT License
Classifier: Operating System :: MacOS :: MacOS X
Classifier: Operating System :: Microsoft :: Windows
Classifier: Operating System :: POSIX
Classifier: Programming Language :: Python :: 3
Classifier: Programming Language :: Python :: 3.7
Classifier: Programming Language :: Python :: 3.8
Classifier: Programming Language :: Python :: 3.9
Classifier: Programming Language :: Python :: 3.10
Classifier: Programming Language :: Python :: 3.11
Classifier: Programming Language :: Python :: 3 :: Only
Classifier: Programming Language :: Python :: Implementation :: CPython
Classifier: Programming Language :: Python :: Implementation :: PyPy
Classifier: Topic :: Software Development :: Libraries
Classifier: Topic :: Security :: Cryptography
Requires-Python: >=3.7
License-File: LICENSE.txt
